README.md
setup.py
efst/__init__.py
efst.egg-info/PKG-INFO
efst.egg-info/SOURCES.txt
efst.egg-info/dependency_links.txt
efst.egg-info/entry_points.txt
efst.egg-info/requires.txt
efst.egg-info/top_level.txt
efst.egg-info/zip-safe
efst/cli/__init__.py
efst/cli/efsb/__init__.py
efst/cli/efsb/efsb_dispatch.py
efst/cli/efsb/efsb_options.py
efst/cli/efsc/__init__.py
efst/cli/efsc/efsc_dispatch.py
efst/cli/efsc/efsc_options.py
efst/cli/efsm/__init__.py
efst/cli/efsm/efsm_dispatch.py
efst/cli/efsm/efsm_options.py
efst/cli/efst/__init__.py
efst/cli/efst/efst_dispatch.py
efst/cli/efst/efst_options.py
efst/cli/efst/checks/__init__.py
efst/cli/efst/checks/chk_encfs.py
efst/cli/efst/checks/chk_pv.py
efst/config/__init__.py
efst/config/efst.conf
efst/config/efst_config.py
efst/encfs/__init__.py
efst/encfs/encfs_cfg.py
efst/encfs/encfs_cmd.py
efst/encfs/encfs_handler.py
efst/utils/__init__.py
efst/utils/efst_utils.py