Metadata-Version: 2.1
Name: efst
Version: 0.27
Summary: 
Home-page: https://github.com/akpw/efst
Author: Arseniy Kuznetsov
Author-email: k.arseniy@gmail.com
License: GNU General Public License v2 (GPLv2)
Keywords: EncFS create manage encrypt decrypt export mount unmount ciphertext plaintext
Platform: UNKNOWN
Classifier: Development Status :: 4 - Beta
Classifier: License :: OSI Approved :: GNU General Public License v2 or later (GPLv2+)
Classifier: Programming Language :: Python
Classifier: Programming Language :: Python :: 3.4
Classifier: Programming Language :: Python :: 3 :: Only
Classifier: Intended Audience :: End Users/Desktop
Classifier: Intended Audience :: Developers
Classifier: Intended Audience :: System Administrators
Classifier: Intended Audience :: Information Technology
Classifier: Operating System :: MacOS
Classifier: Operating System :: POSIX :: Linux
Classifier: Topic :: System
Classifier: Topic :: System :: Systems Administration
Classifier: Topic :: Utilities
